laminarflow/__init__.py
laminarflow/dataset.py
laminarflow-0.0.7.dist-info/METADATA
laminarflow-0.0.7.dist-info/RECORD
laminarflow-0.0.7.dist-info/WHEEL
laminarflow-0.0.7.dist-info/top_level.txt
