Metadata-Version: 2.1
Name: laminarflow
Version: 0.0.7
Summary: Streamline your TensorFlow workflow.
Home-page: https://github.com/elliotwaite/laminarflow
Author: Elliot Waite
Author-email: elliot@elliotwaite.com
License: Apache 2.0
Keywords: laminarflow laminar tensorflow tensor tfrecord tfrecords ml machine learning ai artificial intelligence deep neural network networks
Platform: UNKNOWN
Classifier: Development Status :: 1 - Planning
Classifier: Intended Audience :: Developers
Classifier: Intended Audience :: Education
Classifier: Intended Audience :: Science/Research
Classifier: License :: OSI Approved :: Apache Software License
Classifier: Programming Language :: Python :: 2
Classifier: Programming Language :: Python :: 2.7
Classifier: Programming Language :: Python :: 3
Classifier: Programming Language :: Python :: 3.4
Classifier: Programming Language :: Python :: 3.5
Classifier: Programming Language :: Python :: 3.6
Classifier: Topic :: Scientific/Engineering
Classifier: Topic :: Scientific/Engineering :: Artificial Intelligence
Classifier: Topic :: Scientific/Engineering :: Mathematics
Classifier: Topic :: Software Development
Classifier: Topic :: Software Development :: Libraries
Classifier: Topic :: Software Development :: Libraries :: Python Modules
Requires-Dist: numpy (>=1.13.3)
Requires-Dist: tensorflow (>=1.7.0)
